README.rst
setup.py
licpy/__init__.py
licpy/lic.py
licpy/pixelize.py
licpy/plot.py
licpy/resample.cpp
licpy/resample_wrap.py
licpy.egg-info/PKG-INFO
licpy.egg-info/SOURCES.txt
licpy.egg-info/dependency_links.txt
licpy.egg-info/top_level.txt