Metadata-Version: 1.1
Name: licpy
Version: 0.2
Summary: Line Integral Convolution
Home-page: http://github.com/drufat/licpy.git
Author: Dzhelil Rufat
Author-email: drufat@fastmail.com
License: GNU GPLv3
Platform: UNKNOWN
Requires: pybind11
Requires: numpy
Requires: sympy
Requires: tensorflow
